django3_viewflow-2.0.2.dist-info/DESCRIPTION.rst
django3_viewflow-2.0.2.dist-info/METADATA
django3_viewflow-2.0.2.dist-info/RECORD
django3_viewflow-2.0.2.dist-info/WHEEL
django3_viewflow-2.0.2.dist-info/metadata.json
django3_viewflow-2.0.2.dist-info/top_level.txt
viewflow/__init__.py
viewflow/activation.py
viewflow/admin.py
viewflow/apps.py
viewflow/base.py
viewflow/compat.py
viewflow/decorators.py
viewflow/exceptions.py
viewflow/fields.py
viewflow/forms.py
viewflow/fsm.py
viewflow/lock.py
viewflow/managers.py
viewflow/mixins.py
viewflow/models.py
viewflow/signals.py
viewflow/token.py
viewflow/utils.py
viewflow/flow/__init__.py
viewflow/flow/activation.py
viewflow/flow/nodes.py
viewflow/flow/viewset.py
viewflow/flow/views/__init__.py
viewflow/flow/views/actions.py
viewflow/flow/views/detail.py
viewflow/flow/views/list.py
viewflow/flow/views/mixins.py
viewflow/flow/views/start.py
viewflow/flow/views/task.py
viewflow/flow/views/utils.py
viewflow/frontend/__init__.py
viewflow/frontend/apps.py
viewflow/frontend/models.py
viewflow/frontend/views.py
viewflow/frontend/viewset.py
viewflow/frontend/static/viewflow/css/viewflow.css
viewflow/frontend/static/viewflow/js/jquery.selectable-list.js
viewflow/frontend/static/viewflow/js/viewflow.js
viewflow/frontend/static/viewflow/sass/viewflow.scss
viewflow/frontend/templates/viewflow/base_module.html
viewflow/frontend/templates/viewflow/menu.html
viewflow/frontend/templates/viewflow/site_archive.html
viewflow/frontend/templates/viewflow/site_queue.html
viewflow/frontend/templates/viewflow/site_task_action.html
viewflow/frontend/templates/viewflow/site_tasks.html
viewflow/frontend/templates/viewflow/flow/base_task.html
viewflow/frontend/templates/viewflow/flow/process_cancel.html
viewflow/frontend/templates/viewflow/flow/process_data.html
viewflow/frontend/templates/viewflow/flow/process_detail.html
viewflow/frontend/templates/viewflow/flow/process_list.html
viewflow/frontend/templates/viewflow/flow/queue.html
viewflow/frontend/templates/viewflow/flow/start.html
viewflow/frontend/templates/viewflow/flow/task.html
viewflow/frontend/templates/viewflow/flow/task_action.html
viewflow/frontend/templates/viewflow/flow/task_assign.html
