Metadata-Version: 2.0
Name: django3-viewflow
Version: 2.0.2
Summary: Reusable workflow library for django
Home-page: http://github.com/viewflow/viewflow
Author: Mikhail Podgurskiy
Author-email: kmmbvnr@gmail.com
License: UNKNOWN
Keywords: workflow,django,bpm,automaton
Platform: Any
Classifier: Development Status :: 5 - Production/Stable
Classifier: Intended Audience :: Developers
Classifier: Natural Language :: English
Classifier: Operating System :: OS Independent
Classifier: Framework :: Django
Classifier: Framework :: Django :: 1.11
Classifier: Framework :: Django :: 2.0
Classifier: Framework :: Django :: 2.1
Classifier: Framework :: Django :: 2.2
Classifier: Programming Language :: Python :: 2.7
Classifier: Programming Language :: Python :: 3
Classifier: Programming Language :: Python :: 3.6
Classifier: Programming Language :: Python :: 3.7
Classifier: Topic :: Software Development :: Libraries :: Python Modules
Classifier: License :: OSI Approved :: GNU Affero General Public License v3 or later (AGPLv3+)
Requires-Dist: Django (>=3)
Requires-Dist: django-filter (>=1.0)
Requires-Dist: django-jsonstore
Requires-Dist: django-annoying
Requires-Dist: six
